CHANGES
LICENSE
MANIFEST.in
README.rst
setup.py
holocron_clear_theme/__init__.py
holocron_clear_theme.egg-info/PKG-INFO
holocron_clear_theme.egg-info/SOURCES.txt
holocron_clear_theme.egg-info/dependency_links.txt
holocron_clear_theme.egg-info/entry_points.txt
holocron_clear_theme.egg-info/not-zip-safe
holocron_clear_theme.egg-info/requires.txt
holocron_clear_theme.egg-info/top_level.txt
holocron_clear_theme/theme/static/pygments.css
holocron_clear_theme/theme/static/style.css
holocron_clear_theme/theme/templates/base.html
holocron_clear_theme/theme/templates/document-list.html
holocron_clear_theme/theme/templates/page.html
holocron_clear_theme/theme/templates/post.html