Metadata-Version: 1.1
Name: holocron-clear-theme
Version: 1.0.0
Summary: Holocron Clear Theme
Home-page: http://github.com/ikalnitsky/holocron-clear-theme/
Author: Igor Kalnitsky
Author-email: igor@kalnitsky.org
License: MIT
Keywords: holocron blog generator theme clear simplicity
Platform: UNKNOWN
Classifier: Environment :: Console
Classifier: License :: OSI Approved :: MIT License
Classifier: Operating System :: OS Independent
Classifier: Intended Audience :: End Users/Desktop
Classifier: Intended Audience :: Information Technology
Classifier: Topic :: Internet :: WWW/HTTP
Classifier: Topic :: Terminals
Classifier: Programming Language :: Python
Classifier: Programming Language :: Python :: 3
Classifier: Programming Language :: Python :: 3.3
Classifier: Programming Language :: Python :: 3.4
Classifier: Programming Language :: Python :: 3.5
